{"id": "49625697", "name": "Журналист/писатель (копирайтер)", "area": {"id": "1002", "name": "Минск", "url": "https://api.hh.ru/areas/1002?host=hh.ru"}, "salary": 1, "type": {"id": "open", "name": "Открытая"}, "address": {"city": "Минск", "street": "Коммунистическая улица", "building": "11", "description": null, "lat": 53.912638, "lng": 27.562101, "raw": "Минск, Коммунистическая улица, 11", "metro": null, "metro_stations": []}, "experience": {"id": "between1And3", "name": "От 1 года до 3 лет"}, "schedule": {"id": "fullDay", "name": "Полный день"}, "employment": {"id": "full", "name": "Полная занятость"}, "department": null, "contacts": null, "description": "<p>Выставочное предприятие &quot;Белинтерэкспо&quot; Белорусской торгово-промышленной палаты приглашает в свою команду журналиста, писателя, копирайтера.</p> <p><strong>Преимущества работодателя:</strong></p> <ul> <li>лучшая выставочная компания Беларуси;</li> <li>безусловный лидер в сегменте организации выставочных проектов за рубежом;</li> <li>опыт сотрудничества с ведущими компаниями в Беларуси и за рубежом;</li> <li>офис в центре города;</li> <li>официальное трудоустройство;</li> <li>обучение за счет предприятия;</li> <li>социальный пакет.</li> </ul> <p><strong>Круг обязанностей:</strong></p> <ul> <li>подготовка текстов: новостей, пресс-релизов, статей, интервью, постов в соц.сетях по тематикам: бизнес, экономика, экспорт, выставки, конференции, органические и натуральные продукты, информационные технологии, мода, иное;</li> <li>разработка контент-стратегии и контент-плана;</li> <li>сбор информации и поиск информационных поводов (в том числе, в англоязычных источниках);</li> <li>подбор «говорящих» заголовков и картинок;</li> <li>участие в разработке концепций новых выставочных проектов;</li> <li>размещение текстовых и графических материалов на информационных ресурсах компании и сторонних ресурсах;</li> <li>подготовка части материалов также на английском языке;</li> <li>коммуникации со СМИ Беларуси и других стран;</li> <li>участие в формировании текстовой части презентаций и концепций проектов.</li> </ul> <p><strong>Требования к соискателям:</strong></p> <ul> <li>Опыт написания пресс-релизов, статей по темам: бизнес, экономика, профессиональная публицистика по различным отраслям;</li> <li>Понимание принципов SMM;</li> <li>Безупречная грамотность;</li> <li>Знание английского языка на рабочем уровне;</li> <li>Открытость к изучению нового;</li> <li>Аналитический склад ума, экспертный подход к освещаемой теме;</li> <li>Творческий подход к решаемой задаче;</li> <li>Позитивное мировосприятие.</li> </ul> <p><strong>Условия:</strong></p> <ul> <li>конкурентная оплата труда;</li> <li>оклад + премии;</li> <li>официальное трудоустройство;</li> <li>обучение за счет предприятия;</li> <li>корпоративное медицинское страхование;</li> <li>интересная работа в дружном коллективе;</li> <li>офис в центре города;</li> <li>график работы: пн-чт, с 8.30 до 17.30, пт, с 8:30 до 16:15</li> </ul> <p>Сопроводительное письмо со ссылкой на примеры своих статей и работ является обязательным требованием.</p> <p>Собеседования проводятся по результатам рассмотренных резюме.</p> <p> </p>", "branded_description": null, "vacancy_constructor_template": null, "key_skills": [{"name": "Написание пресс-релизов"}, {"name": "Написание статей"}, {"name": "PR"}, {"name": "Грамотность"}, {"name": "Планирование рекламных кампаний"}, {"name": "Журналистика"}, {"name": "Работа со СМИ"}, {"name": "Управление проектами"}, {"name": "Английский язык"}, {"name": "Деловая коммуникация"}], "accept_handicapped": false, "accept_kids": false, "archived": false, "specializations": [{"id": "11.76", "name": "Издательская деятельность", "profarea_id": "11", "profarea_name": "Искусство, развлечения, масс-медиа"}, {"id": "11.243", "name": "Радио", "profarea_id": "11", "profarea_name": "Искусство, развлечения, масс-медиа"}, {"id": "11.293", "name": "Телевидение", "profarea_id": "11", "profarea_name": "Искусство, развлечения, масс-медиа"}, {"id": "11.71", "name": "Журналистика", "profarea_id": "11", "profarea_name": "Искусство, развлечения, масс-медиа"}, {"id": "11.745", "name": "Корректор, ретушер", "profarea_id": "11", "profarea_name": "Искусство, развлечения, масс-медиа"}, {"id": "11.218", "name": "Пресса", "profarea_id": "11", "profarea_name": "Искусство, развлечения, масс-медиа"}], "professional_roles": [{"id": "55", "name": "Копирайтер, редактор, корректор"}], "driver_license_types": [], "employer": {"id": "1400641", "name": "Белинтерэкспо", "url": "https://api.hh.ru/employers/1400641?host=hh.ru", "alternate_url": "https://hh.ru/employer/1400641", "logo_urls": {"original": "https://hhcdn.ru/employer-logo-original/33075.png", "90": "https://hhcdn.ru/employer-logo/966683.png"}, "vacancies_url": "https://api.hh.ru/vacancies?employer_id=1400641&host=hh.ru", "trusted": true}, "published_at": "2022-05-02T12:43:32+0300", "created_at": "2022-05-02T12:43:32+0300", "test": null, "alternate_url": "https://hh.ru/vacancy/49625697", "working_days": [], "working_time_intervals": [], "working_time_modes": [], "accept_temporary": true, "description_cleaned": "выставочное предприятие ;белинтерэкспо; белорусской торгово-промышленной палаты приглашает в свою команду журналиста, писателя, копирайтера. преимущества работодателя:  лучшая выставочная компания беларуси; безусловный лидер в сегменте организации выставочных проектов за рубежом; опыт сотрудничества с ведущими компаниями в беларуси и за рубежом; офис в центре города; официальное трудоустройство; обучение за счет предприятия; социальный пакет.  круг обязанностей:  подготовка текстов: новостей, пресс-релизов, статей, интервью, постов в соц.сетях по тематикам: бизнес, экономика, экспорт, выставки, конференции, органические и натуральные продукты, информационные технологии, мода, иное; разработка контент-стратегии и контент-плана; сбор информации и поиск информационных поводов (в том числе, в англоязычных источниках); подбор «говорящих» заголовков и картинок; участие в разработке концепций новых выставочных проектов; размещение текстовых и графических материалов на информационных ресурсах компании и сторонних ресурсах; подготовка части материалов также на английском языке; коммуникации со сми беларуси и других стран; участие в формировании текстовой части презентаций и концепций проектов.  требования к соискателям:  опыт написания пресс-релизов, статей по темам: бизнес, экономика, профессиональная публицистика по различным отраслям; понимание принципов smm; безупречная грамотность; знание английского языка на рабочем уровне; открытость к изучению нового; аналитический склад ума, экспертный подход к освещаемой теме; творческий подход к решаемой задаче; позитивное мировосприятие.  условия:  конкурентная оплата труда; оклад + премии; официальное трудоустройство; обучение за счет предприятия; корпоративное медицинское страхование; интересная работа в дружном коллективе; офис в центре города; график работы: пн-чт, с 8.30 до 17.30, пт, с 8:30 до 16:15  сопроводительное письмо со ссылкой на примеры своих статей и работ является обязательным требованием. собеседования проводятся по результатам рассмотренных резюме.  ", "bonus_description": ":  конкурентная оплата труда; оклад + премии; официальное трудоустройство; обучение за счет предприятия; корпоративное медицинское страхование; интересная работа в дружном коллективе; офис в центре города; график работы: пн-чт, с 8.30 до 17.30, пт, с 8:30 до 16:15  сопроводительное письмо со ссылкой на примеры своих статей и работ является обязательным требованием. собеседования проводятся по результатам рассмотренных резюме.  ", "official": 1, "living": 0, "vacation": 0, "coworkers": 1, "office": 1, "education": 1, "location": 1, "extra": 1, "growth": 0, "tasks": 0, "dms": 1, "social": 0, "discount": 0, "hours": 1, "disko": 0, "food": 0, "remote": 0, "drive": 0, "hotel": 0, "tech": 0, "clothes": 0, "sport": 0}