{"id": "55129534", "name": "Монтажник", "area": {"id": "2492", "name": "Баку", "url": "https://api.hh.ru/areas/2492?host=hh.ru"}, "salary": 0, "type": {"id": "open", "name": "Открытая"}, "address": null, "experience": {"id": "between3And6", "name": "От 3 до 6 лет"}, "schedule": {"id": "fullDay", "name": "Полный день"}, "employment": {"id": "full", "name": "Полная занятость"}, "department": null, "contacts": null, "description": "<strong>Обязанности:</strong> <p>- монтаж и ремонт высоковольтных воздушных и подземных линий электропередачи и линий контактных сетей электротяги;<br />- соединение кабелей воздушных и подземных сетей;<br />- соблюдение правил и процедур техники безопасности, в том числе регулярная проверка оборудования и возведение ограждений вокруг мест проведения работ;<br />- размыкание переключателей или подсоединение заземляющих устройств для устранения опасности поражения электрическим током от неисправных или упавших линий, а также в целях облегчения проведения ремонтных работ;<br />- подъем на столбы или использование автомобильных подъемников для доступа к оборудованию;<br />- выявление неисправных секционных устройств, размыкателей, плавких предохранителей, регуляторов напряжения, трансформаторов, переключателей, реле или проводки с использованием схем электропроводки и электрических контрольно-измерительных приборов.</p> <strong>Требования:</strong> <ul> <li>опыт работы в сфере высоковольтных воздушных и подземных линий электропередачи и линий контактных сетей электротяги</li> <li>знание английского языка на среднем уровне</li> </ul>", "branded_description": null, "vacancy_constructor_template": null, "key_skills": [{"name": "Английский язык"}, {"name": "Работа в команде"}, {"name": "Ремонтные работы"}, {"name": "3 группа по электробезопасности"}], "accept_handicapped": false, "accept_kids": false, "archived": false, "specializations": [{"id": "20.287", "name": "Строительство", "profarea_id": "20", "profarea_name": "Строительство, недвижимость"}, {"id": "20.490", "name": "Рабочие строительных специальностей", "profarea_id": "20", "profarea_name": "Строительство, недвижимость"}, {"id": "29.517", "name": "Сборщик", "profarea_id": "29", "profarea_name": "Рабочий персонал"}, {"id": "29.581", "name": "Монтажник", "profarea_id": "29", "profarea_name": "Рабочий персонал"}, {"id": "29.583", "name": "Маляр", "profarea_id": "29", "profarea_name": "Рабочий персонал"}], "professional_roles": [{"id": "78", "name": "Монтажник"}], "driver_license_types": [], "employer": {"id": "6166569", "name": "HRC", "url": "https://api.hh.ru/employers/6166569?host=hh.ru", "alternate_url": "https://hh.ru/employer/6166569", "logo_urls": null, "vacancies_url": "https://api.hh.ru/vacancies?employer_id=6166569&host=hh.ru", "trusted": true}, "published_at": "2022-04-28T15:28:03+0300", "created_at": "2022-04-28T15:28:03+0300", "test": null, "alternate_url": "https://hh.ru/vacancy/55129534", "working_days": [], "working_time_intervals": [], "working_time_modes": [], "accept_temporary": false, "description_cleaned": "обязанности: - монтаж и ремонт высоковольтных воздушных и подземных линий электропередачи и линий контактных сетей электротяги;- соединение кабелей воздушных и подземных сетей;- соблюдение правил и процедур техники безопасности, в том числе регулярная проверка оборудования и возведение ограждений вокруг мест проведения работ;- размыкание переключателей или подсоединение заземляющих устройств для устранения опасности поражения электрическим током от неисправных или упавших линий, а также в целях облегчения проведения ремонтных работ;- подъем на столбы или использование автомобильных подъемников для доступа к оборудованию;- выявление неисправных секционных устройств, размыкателей, плавких предохранителей, регуляторов напряжения, трансформаторов, переключателей, реле или проводки с использованием схем электропроводки и электрических контрольно-измерительных приборов. требования:  опыт работы в сфере высоковольтных воздушных и подземных линий электропередачи и линий контактных сетей электротяги знание английского языка на среднем уровне ", "bonus_description": "", "official": 0, "living": 0, "vacation": 0, "coworkers": 0, "office": 0, "education": 0, "location": 0, "extra": 0, "growth": 0, "tasks": 0, "dms": 0, "social": 0, "discount": 0, "hours": 0, "disko": 0, "food": 0, "remote": 0, "drive": 0, "hotel": 0, "tech": 0, "clothes": 0, "sport": 0}