{"id": "55047895", "name": "Директор на производство", "area": {"id": "177", "name": "Караганда", "url": "https://api.hh.ru/areas/177?host=hh.ru"}, "salary": 0, "type": {"id": "open", "name": "Открытая"}, "address": {"city": "Караганда", "street": null, "building": null, "description": null, "lat": 49.80776, "lng": 73.088504, "raw": "Караганда", "metro": null, "metro_stations": []}, "experience": {"id": "between1And3", "name": "От 1 года до 3 лет"}, "schedule": {"id": "fullDay", "name": "Полный день"}, "employment": {"id": "full", "name": "Полная занятость"}, "department": null, "contacts": null, "description": "<p>Требуемый опыт работы: 1год</p> <p>Полная занятость, полный день</p> <p>Наша компания занимается переработкой овощей в городе Караганда. Всю информацию можете просмотреть на сайте: QazAgroFood или в YouTube chanel.<br /><br />Требуется директор для создания команды с 0. Нужно нанять сотрудников производства,<br /><br />Нужны амбициозные люди с предпринимательским мышлением.<br /><br />Оплата 200 000 - 650 000 тенге</p>", "branded_description": null, "vacancy_constructor_template": null, "key_skills": [{"name": "Творческое мышление"}, {"name": "Гибкость"}, {"name": "Многозадачность"}, {"name": "Терпеливость"}], "accept_handicapped": false, "accept_kids": false, "archived": false, "specializations": [{"id": "18.142", "name": "Машиностроение", "profarea_id": "18", "profarea_name": "Производство, сельское хозяйство"}, {"id": "18.451", "name": "Управление проектами", "profarea_id": "18", "profarea_name": "Производство, сельское хозяйство"}, {"id": "18.263", "name": "Руководство предприятием", "profarea_id": "18", "profarea_name": "Производство, сельское хозяйство"}, {"id": "18.330", "name": "Управление цехом", "profarea_id": "18", "profarea_name": "Производство, сельское хозяйство"}, {"id": "9.238", "name": "Производство, Технология", "profarea_id": "9", "profarea_name": "Высший менеджмент"}], "professional_roles": [{"id": "80", "name": "Начальник производства"}], "driver_license_types": [], "employer": {"id": "4968248", "name": "Qazagrofood Logistic", "url": "https://api.hh.ru/employers/4968248?host=hh.ru", "alternate_url": "https://hh.ru/employer/4968248", "logo_urls": null, "vacancies_url": "https://api.hh.ru/vacancies?employer_id=4968248&host=hh.ru", "trusted": true}, "published_at": "2022-04-25T16:23:42+0300", "created_at": "2022-04-25T16:23:42+0300", "test": null, "alternate_url": "https://hh.ru/vacancy/55047895", "working_days": [], "working_time_intervals": [], "working_time_modes": [], "accept_temporary": false, "description_cleaned": "требуемый опыт работы: 1год полная занятость, полный день наша компания занимается переработкой овощей в городе караганда. всю информацию можете просмотреть на сайте: qazagrofood или в youtube chanel.требуется директор для создания команды с 0. нужно нанять сотрудников производства,нужны амбициозные люди с предпринимательским мышлением.оплата 200 000 - 650 000 тенге", "bonus_description": "", "official": 0, "living": 0, "vacation": 0, "coworkers": 0, "office": 0, "education": 0, "location": 0, "extra": 0, "growth": 0, "tasks": 0, "dms": 0, "social": 0, "discount": 0, "hours": 0, "disko": 0, "food": 0, "remote": 0, "drive": 0, "hotel": 0, "tech": 0, "clothes": 0, "sport": 0}