{"id": "55090687", "name": "Координатор/Менеджер образовательных программ (семинаров, курсов, конференций)", "area": {"id": "1", "name": "Москва", "url": "https://api.hh.ru/areas/1?host=hh.ru"}, "salary": 1, "type": {"id": "open", "name": "Открытая"}, "address": {"city": "Москва", "street": "проспект Мира", "building": "16с2", "description": null, "lat": 55.775297, "lng": 37.632817, "raw": "Москва, проспект Мира, 16с2", "metro": null, "metro_stations": []}, "experience": {"id": "between1And3", "name": "От 1 года до 3 лет"}, "schedule": {"id": "fullDay", "name": "Полный день"}, "employment": {"id": "full", "name": "Полная занятость"}, "department": null, "contacts": null, "description": "<strong>Обязанности:</strong> <ul> <li>взаимодействие со спикерами, приглашение на выступление, заключение договоров, составление расписания, сопровождение семинаров и курсов, сбор обратной связи;</li> <li>актуализация имеющихся программ семинаров/курсов, поиск и предложение новых актуальных (продаваемых) тем семинаров и курсов, разработка новых программ (вместе с потенциальными спикерами)</li> <li>совместно с техническими специалистами запись курсов и формирование автоматизированных онлайн программ;</li> <li>совместно со спикерами формирование описания курсов, разработка образовательных программ.</li> </ul> <strong>Требования:</strong> <ul> <li>высшее образование;</li> <li>опыт практической работы;</li> <li>умение работать с большими объемами информации; анализировать информацию и делать правильные выводы.</li> <li>умение излагать информацию в письменной форме;</li> <li>хорошо развитые коммуникативные навыки;</li> <li>внимательность, ответственность, высокая обучаемость</li> <li>стремление к совершенствованию профессиональных качеств и навыков.</li> </ul> <strong>Условия:</strong> <ul> <li>оклад 60 000 + бонусы по итогам мероприятий);</li> <li>по согласованию - возможна ЧАСТИЧНО дистанционная работа;</li> </ul>", "branded_description": null, "vacancy_constructor_template": null, "key_skills": [{"name": "Пользователь ПК"}, {"name": "Грамотная речь"}, {"name": "Работа с большим объемом информации"}, {"name": "Поиск информации в интернет"}, {"name": "Заключение договоров"}, {"name": "Организаторские навыки"}, {"name": "Организация мероприятий"}, {"name": "разработка образовательных программ"}], "accept_handicapped": false, "accept_kids": false, "archived": false, "specializations": [{"id": "6.309", "name": "Тренинги", "profarea_id": "6", "profarea_name": "Управление персоналом, тренинги"}, {"id": "6.247", "name": "Развитие персонала", "profarea_id": "6", "profarea_name": "Управление персоналом, тренинги"}], "professional_roles": [{"id": "17", "name": "Бизнес-тренер"}], "driver_license_types": [], "employer": {"id": "3178673", "name": "ЦСП Инклюзивная молекула", "url": "https://api.hh.ru/employers/3178673?host=hh.ru", "alternate_url": "https://hh.ru/employer/3178673", "logo_urls": {"240": "https://hhcdn.ru/employer-logo/3808956.png", "90": "https://hhcdn.ru/employer-logo/3808955.png", "original": "https://hhcdn.ru/employer-logo-original/842020.png"}, "vacancies_url": "https://api.hh.ru/vacancies?employer_id=3178673&host=hh.ru", "trusted": true}, "published_at": "2022-04-27T10:36:15+0300", "created_at": "2022-04-27T10:36:15+0300", "test": null, "alternate_url": "https://hh.ru/vacancy/55090687", "working_days": [], "working_time_intervals": [], "working_time_modes": [], "accept_temporary": false, "description_cleaned": "обязанности:  взаимодействие со спикерами, приглашение на выступление, заключение договоров, составление расписания, сопровождение семинаров и курсов, сбор обратной связи; актуализация имеющихся программ семинаров/курсов, поиск и предложение новых актуальных (продаваемых) тем семинаров и курсов, разработка новых программ (вместе с потенциальными спикерами) совместно с техническими специалистами запись курсов и формирование автоматизированных онлайн программ; совместно со спикерами формирование описания курсов, разработка образовательных программ.  требования:  высшее образование; опыт практической работы; умение работать с большими объемами информации; анализировать информацию и делать правильные выводы. умение излагать информацию в письменной форме; хорошо развитые коммуникативные навыки; внимательность, ответственность, высокая обучаемость стремление к совершенствованию профессиональных качеств и навыков.  условия:  оклад 60 000 + бонусы по итогам мероприятий); по согласованию - возможна частично дистанционная работа; ", "bonus_description": ":  оклад 60 000 + бонусы по итогам мероприятий); по согласованию - возможна частично дистанционная работа; ", "official": 0, "living": 0, "vacation": 0, "coworkers": 0, "office": 0, "education": 0, "location": 0, "extra": 1, "growth": 0, "tasks": 0, "dms": 0, "social": 0, "discount": 0, "hours": 0, "disko": 1, "food": 0, "remote": 0, "drive": 0, "hotel": 0, "tech": 0, "clothes": 0, "sport": 0}