{"id": "51359253", "name": "Программист Frontend", "area": {"id": "1", "name": "Москва", "url": "https://api.hh.ru/areas/1?host=hh.ru"}, "salary": 0, "type": {"id": "open", "name": "Открытая"}, "address": null, "experience": {"id": "between1And3", "name": "От 1 года до 3 лет"}, "schedule": {"id": "fullDay", "name": "Полный день"}, "employment": {"id": "full", "name": "Полная занятость"}, "department": null, "contacts": null, "description": "<p><em>Мы - коммерческая компания, разработчик комплексных систем безопасности, ситуационных центров и систем поддержки принятия решений.</em></p> <p><em>Нам доверяют сложнейшие IT задачи для обеспечения национальной безопасности. Наши продукты используют десятки тысяч пользователей ежедневно.</em></p> <p><em>У нас более 15 команд разработки и масса интересных задач! </em></p> <p><strong>Работа с нами — это:</strong></p> <ul> <li><strong>Участие в масштабных проектах:</strong> Высоконагруженные информационные системы, системы управления инфраструктурой городов на основе машинного обучения, системы потокового распознавания аудио и видео информации;</li> </ul> <ul> <li><strong>Команда:</strong> работа с экспертами в IT области;</li> </ul> <ul> <li><strong>Возможности профессионального развития:</strong> мы организуем онлайн и офлайн митапы на актуальные темы, внутренние технические и архитектурные встречи по обмену опытом;</li> </ul> <ul> <li><strong>Следование современным трендам:</strong> Gitlab, настроенный CI/CD, набор инструментов Jira/Confluence, K8S, корпоративный мессенджер, система видеоконференций, <strong>удаленная работа в гибридном формате</strong>;</li> </ul> <ul> <li><strong>Программа ДМС</strong> со стоматологией, а для позитивной рабочей атмосферы фрукты, зерновой кофе и снеки.</li> </ul> <ul> <li>Конкурентоспособная ЗП (обсуждается с успешным кандидатом);</li> </ul> <p><strong>Задачи:</strong></p> <ul> <li>Разработка программного обеспечения военного и гражданского назначения;</li> <li>Участие в проектировании интерфейса приложений;</li> <li>Интеграция с внутренними API;</li> <li>Поддержка реализованного функционала;</li> <li>Проведение код-ревью;</li> </ul> <p><strong>Необходимые профессиональные знания и навыки:</strong></p> <ul> <li>Angular (или знание других JavaScript-фреймворков React, Vue и желание изучить Angular);</li> <li>JavaScript (будет плюсом знание TypeScript);</li> <li>HTML, CSS;</li> <li>Git;</li> <li>OC Linux;</li> </ul>", "branded_description": null, "vacancy_constructor_template": null, "key_skills": [{"name": "Git"}, {"name": "JavaScript"}, {"name": "TypeScript"}, {"name": "Linux"}, {"name": "Atlassian Jira"}], "accept_handicapped": false, "accept_kids": false, "archived": false, "specializations": [{"id": "1.221", "name": "Программирование, Разработка", "profarea_id": "1", "profarea_name": "Информационные технологии, интернет, телеком"}, {"id": "1.82", "name": "Инженер", "profarea_id": "1", "profarea_name": "Информационные технологии, интернет, телеком"}, {"id": "1.744", "name": "Другое", "profarea_id": "1", "profarea_name": "Информационные технологии, интернет, телеком"}, {"id": "1.9", "name": "Web инженер", "profarea_id": "1", "profarea_name": "Информационные технологии, интернет, телеком"}], "professional_roles": [{"id": "96", "name": "Программист, разработчик"}], "driver_license_types": [], "employer": {"id": "103944", "name": "РТИ", "url": "https://api.hh.ru/employers/103944?host=hh.ru", "alternate_url": "https://hh.ru/employer/103944", "logo_urls": {"240": "https://hhcdn.ru/employer-logo/2909165.jpeg", "90": "https://hhcdn.ru/employer-logo/2909164.jpeg", "original": "https://hhcdn.ru/employer-logo-original/617003.JPG"}, "vacancies_url": "https://api.hh.ru/vacancies?employer_id=103944&host=hh.ru", "trusted": true}, "published_at": "2022-04-11T12:34:03+0300", "created_at": "2022-04-11T12:34:03+0300", "test": null, "alternate_url": "https://hh.ru/vacancy/51359253", "working_days": [], "working_time_intervals": [], "working_time_modes": [], "accept_temporary": false, "description_cleaned": "мы - коммерческая компания, разработчик комплексных систем безопасности, ситуационных центров и систем поддержки принятия решений. нам доверяют сложнейшие it задачи для обеспечения национальной безопасности. наши продукты используют десятки тысяч пользователей ежедневно. у нас более 15 команд разработки и масса интересных задач!  работа с нами — это:  участие в масштабных проектах: высоконагруженные информационные системы, системы управления инфраструктурой городов на основе машинного обучения, системы потокового распознавания аудио и видео информации;   команда: работа с экспертами в it области;   возможности профессионального развития: мы организуем онлайн и офлайн митапы на актуальные темы, внутренние технические и архитектурные встречи по обмену опытом;   следование современным трендам: gitlab, настроенный ci/cd, набор инструментов jira/confluence, k8s, корпоративный мессенджер, система видеоконференций, удаленная работа в гибридном формате;   программа дмс со стоматологией, а для позитивной рабочей атмосферы фрукты, зерновой кофе и снеки.   конкурентоспособная зп (обсуждается с успешным кандидатом);  задачи:  разработка программного обеспечения военного и гражданского назначения; участие в проектировании интерфейса приложений; интеграция с внутренними api; поддержка реализованного функционала; проведение код-ревью;  необходимые профессиональные знания и навыки:  angular (или знание других javascript-фреймворков react, vue и желание изучить angular); javascript (будет плюсом знание typescript); html, css; git; oc linux; ", "bonus_description": "", "official": 0, "living": 0, "vacation": 0, "coworkers": 0, "office": 0, "education": 0, "location": 0, "extra": 0, "growth": 0, "tasks": 0, "dms": 0, "social": 0, "discount": 0, "hours": 0, "disko": 0, "food": 0, "remote": 0, "drive": 0, "hotel": 0, "tech": 0, "clothes": 0, "sport": 0}